{
  "comment": "Generated from BHoM RDF_Prototypes",
  "namespace": [],
  "class": [
    {
      "id": "BH.oM.Versioning.VersioningEvent",
      "type": "owl:Class"
    },
    {
      "id": "OldDocument-4C64C95955DF4549D6080EDBF8D78FFB89D5AEC541FE63D1C76137ACBF6200F5-VersioningEvent-HasProperty",
      "type": "rdfs:Datatype"
    },
    {
      "id": "NewDocument-95F48905579F7CA0A3AC7540FAA1F5DDAC4F6D39DD3EBF45CA5438FBE630502E-VersioningEvent-HasProperty",
      "type": "rdfs:Datatype"
    },
    {
      "id": "OldVersion-C0FFFD5B14CC9E67B03D4CCA75A256F6DBCCAE7E4EF151507371F8FC2AB27A7A-VersioningEvent-HasProperty",
      "type": "rdfs:Datatype"
    },
    {
      "id": "NewVersion-8AA6553A185D94A7B93CEFAFDBD486E88A47B7E443A2F22FEE6E886E21145CDE-VersioningEvent-HasProperty",
      "type": "rdfs:Datatype"
    },
    {
      "id": "BH.oM.Versioning.VersioningEvent.Type",
      "type": "owl:Class"
    },
    {
      "id": "BH.oM.Base.Debugging.EventType",
      "type": "owl:Class"
    },
    {
      "id": "BH.oM.Base.IBHoMObject",
      "type": "owl:Class"
    },
    {
      "id": "BH.oM.Base.IObject",
      "type": "owl:Class"
    },
    {
      "id": "BH.oM.Base.Debugging.Event",
      "type": "owl:Class"
    }
  ],
  "classAttribute": [
    {
      "id": "BH.oM.Versioning.VersioningEvent",
      "iri": "https://github.com/BHoM/BHoM/blob/main/Versioning_oM/VersioningEvent.cs",
      "label": "VersioningEvent (BH.oM.Versioning)",
      "attributes": []
    },
    {
      "id": "OldDocument-4C64C95955DF4549D6080EDBF8D78FFB89D5AEC541FE63D1C76137ACBF6200F5-VersioningEvent-HasProperty",
      "iri": "http://www.w3.org/2001/XMLSchema#",
      "label": "OldDocument (String)",
      "attributes": "datatype"
    },
    {
      "id": "NewDocument-95F48905579F7CA0A3AC7540FAA1F5DDAC4F6D39DD3EBF45CA5438FBE630502E-VersioningEvent-HasProperty",
      "iri": "http://www.w3.org/2001/XMLSchema#",
      "label": "NewDocument (String)",
      "attributes": "datatype"
    },
    {
      "id": "OldVersion-C0FFFD5B14CC9E67B03D4CCA75A256F6DBCCAE7E4EF151507371F8FC2AB27A7A-VersioningEvent-HasProperty",
      "iri": "http://www.w3.org/2001/XMLSchema#",
      "label": "OldVersion (String)",
      "attributes": "datatype"
    },
    {
      "id": "NewVersion-8AA6553A185D94A7B93CEFAFDBD486E88A47B7E443A2F22FEE6E886E21145CDE-VersioningEvent-HasProperty",
      "iri": "http://www.w3.org/2001/XMLSchema#",
      "label": "NewVersion (String)",
      "attributes": "datatype"
    },
    {
      "id": "BH.oM.Versioning.VersioningEvent.Type",
      "iri": "https://github.com/BHoM/BHoM/blob/main/BHoM/Debugging/EventType.cs",
      "label": "Type",
      "attributes": []
    },
    {
      "id": "BH.oM.Base.Debugging.EventType",
      "iri": "https://github.com/BHoM/BHoM/blob/main/BHoM/Debugging/EventType.cs",
      "label": "EventType",
      "attributes": []
    },
    {
      "id": "BH.oM.Base.IBHoMObject",
      "iri": "https://github.com/BHoM/BHoM/blob/main/BHoM/Interface/IBHoMObject.cs",
      "label": "IBHoMObject",
      "attributes": []
    },
    {
      "id": "BH.oM.Base.IObject",
      "iri": "https://github.com/BHoM/BHoM/blob/main/BHoM/Interface/IObject.cs",
      "label": "IObject",
      "attributes": []
    },
    {
      "id": "BH.oM.Base.Debugging.Event",
      "iri": "https://github.com/BHoM/BHoM/blob/main/BHoM/Debugging/Event.cs",
      "label": "Event",
      "attributes": []
    }
  ],
  "property": [
    {
      "id": "BH.oM.Versioning.VersioningEvent-BH.oM.RDF.HasProperty-System.String OldDocument",
      "type": "owl:DatatypeProperty"
    },
    {
      "id": "BH.oM.Versioning.VersioningEvent-BH.oM.RDF.HasProperty-System.String NewDocument",
      "type": "owl:DatatypeProperty"
    },
    {
      "id": "BH.oM.Versioning.VersioningEvent-BH.oM.RDF.HasProperty-System.String OldVersion",
      "type": "owl:DatatypeProperty"
    },
    {
      "id": "BH.oM.Versioning.VersioningEvent-BH.oM.RDF.HasProperty-System.String NewVersion",
      "type": "owl:DatatypeProperty"
    },
    {
      "id": "BH.oM.Versioning.VersioningEvent.Type-IsA-BH.oM.Base.Debugging.EventType",
      "type": "owl:ObjectProperty"
    },
    {
      "id": "BH.oM.Versioning.VersioningEvent-BH.oM.RDF.HasProperty-BH.oM.Base.Debugging.EventType Type",
      "type": "owl:ObjectProperty"
    },
    {
      "id": "BH.oM.Versioning.VersioningEvent-BH.oM.RDF.IsA-BH.oM.Base.IBHoMObject",
      "type": "owl:ObjectProperty"
    },
    {
      "id": "BH.oM.Versioning.VersioningEvent-BH.oM.RDF.IsA-BH.oM.Base.IObject",
      "type": "owl:ObjectProperty"
    },
    {
      "id": "BH.oM.Versioning.VersioningEvent-BH.oM.RDF.IsSubclassOf-BH.oM.Base.Debugging.Event",
      "type": "owl:ObjectProperty"
    }
  ],
  "propertyAttribute": [
    {
      "id": "BH.oM.Versioning.VersioningEvent-BH.oM.RDF.HasProperty-System.String OldDocument",
      "iri": "http://visualdataweb.org/newOntology/BH.oM.Versioning.VersioningEvent-BH.oM.RDF.HasProperty-System.String OldDocument",
      "label": "HasProperty",
      "attributes": "datatype",
      "domain": "BH.oM.Versioning.VersioningEvent",
      "range": "OldDocument-4C64C95955DF4549D6080EDBF8D78FFB89D5AEC541FE63D1C76137ACBF6200F5-VersioningEvent-HasProperty"
    },
    {
      "id": "BH.oM.Versioning.VersioningEvent-BH.oM.RDF.HasProperty-System.String NewDocument",
      "iri": "http://visualdataweb.org/newOntology/BH.oM.Versioning.VersioningEvent-BH.oM.RDF.HasProperty-System.String NewDocument",
      "label": "HasProperty",
      "attributes": "datatype",
      "domain": "BH.oM.Versioning.VersioningEvent",
      "range": "NewDocument-95F48905579F7CA0A3AC7540FAA1F5DDAC4F6D39DD3EBF45CA5438FBE630502E-VersioningEvent-HasProperty"
    },
    {
      "id": "BH.oM.Versioning.VersioningEvent-BH.oM.RDF.HasProperty-System.String OldVersion",
      "iri": "http://visualdataweb.org/newOntology/BH.oM.Versioning.VersioningEvent-BH.oM.RDF.HasProperty-System.String OldVersion",
      "label": "HasProperty",
      "attributes": "datatype",
      "domain": "BH.oM.Versioning.VersioningEvent",
      "range": "OldVersion-C0FFFD5B14CC9E67B03D4CCA75A256F6DBCCAE7E4EF151507371F8FC2AB27A7A-VersioningEvent-HasProperty"
    },
    {
      "id": "BH.oM.Versioning.VersioningEvent-BH.oM.RDF.HasProperty-System.String NewVersion",
      "iri": "http://visualdataweb.org/newOntology/BH.oM.Versioning.VersioningEvent-BH.oM.RDF.HasProperty-System.String NewVersion",
      "label": "HasProperty",
      "attributes": "datatype",
      "domain": "BH.oM.Versioning.VersioningEvent",
      "range": "NewVersion-8AA6553A185D94A7B93CEFAFDBD486E88A47B7E443A2F22FEE6E886E21145CDE-VersioningEvent-HasProperty"
    },
    {
      "id": "BH.oM.Versioning.VersioningEvent.Type-IsA-BH.oM.Base.Debugging.EventType",
      "iri": "https://github.com/BHoM/RDF_Prototypes/blob/main/RDF_oM/IsA.cs",
      "label": "IsA",
      "attributes": "object",
      "domain": "BH.oM.Versioning.VersioningEvent.Type",
      "range": "BH.oM.Base.Debugging.EventType"
    },
    {
      "id": "BH.oM.Versioning.VersioningEvent-BH.oM.RDF.HasProperty-BH.oM.Base.Debugging.EventType Type",
      "iri": "http://visualdataweb.org/newOntology/BH.oM.Versioning.VersioningEvent-BH.oM.RDF.HasProperty-BH.oM.Base.Debugging.EventType Type",
      "label": "HasProperty",
      "attributes": [],
      "domain": "BH.oM.Versioning.VersioningEvent",
      "range": "BH.oM.Versioning.VersioningEvent.Type"
    },
    {
      "id": "BH.oM.Versioning.VersioningEvent-BH.oM.RDF.IsA-BH.oM.Base.IBHoMObject",
      "iri": "http://visualdataweb.org/newOntology/BH.oM.Versioning.VersioningEvent-BH.oM.RDF.IsA-BH.oM.Base.IBHoMObject",
      "label": "IsA",
      "attributes": "object",
      "domain": "BH.oM.Versioning.VersioningEvent",
      "range": "BH.oM.Base.IBHoMObject"
    },
    {
      "id": "BH.oM.Versioning.VersioningEvent-BH.oM.RDF.IsA-BH.oM.Base.IObject",
      "iri": "http://visualdataweb.org/newOntology/BH.oM.Versioning.VersioningEvent-BH.oM.RDF.IsA-BH.oM.Base.IObject",
      "label": "IsA",
      "attributes": "object",
      "domain": "BH.oM.Versioning.VersioningEvent",
      "range": "BH.oM.Base.IObject"
    },
    {
      "id": "BH.oM.Versioning.VersioningEvent-BH.oM.RDF.IsSubclassOf-BH.oM.Base.Debugging.Event",
      "iri": "http://visualdataweb.org/newOntology/BH.oM.Versioning.VersioningEvent-BH.oM.RDF.IsSubclassOf-BH.oM.Base.Debugging.Event",
      "label": "IsSubclassOf",
      "attributes": "object",
      "domain": "BH.oM.Versioning.VersioningEvent",
      "range": "BH.oM.Base.Debugging.Event"
    }
  ]
}